[{"ID":8325465,"EventID":1451,"Round":15,"Number":1,"Player1ID":224,"Score1":7,"Walkover1":false,"Player2ID":5,"Score2":10,"Walkover2":false,"WinnerID":5,"Unfinished":false,"OnBreak":false,"Status":3,"WorldSnookerID":0,"LiveUrl":"","DetailsUrl":"","PointsDropped":false,"ShowCommonNote":true,"Estimated":false,"Type":1,"TableNo":0,"VideoURL":"","InitDate":"2023-10-27T08:08:19Z","ModDate":"2023-12-03T13:10:30Z","StartDate":"2023-12-03T13:10:30Z","EndDate":"2023-12-03T21:39:56Z","ScheduledDate":"2023-12-03T19:00:00Z","FrameScores":"Session 1:<br/>0-96 (71), 63-71 (63, 71), 38-91 (91), 99-31 (89)<br/>49-60, 71-19, 115-0 (114), 76-0 (70)<br/><br/>Session 2:<br/>0-89 (84), 56-2 (56), 6-127 (87), 6-80 (79)<br/>70-4 (52), 104-4 (104), 0-100 (100), 8-87 (74), 6-134 (129)","Sessions":"","Note":"Referee: <a href=\"https://twitter.com/RobSpencer147\">Rob Spencer</a><br/><br/>This was O'Sullivan's record-extending eighth UK title and record-extending 40th ranking title.<br/><br/>He now has the records for both youngest and oldest to win the UK Championship.","ExtendedNote":"","HeldOver":false,"StatsURL":""},{"ID":8483188,"EventID":1451,"Round":14,"Number":1,"Player1ID":224,"Score1":6,"Walkover1":false,"Player2ID":12,"Score2":4,"Walkover2":false,"WinnerID":224,"Unfinished":false,"OnBreak":false,"Status":3,"WorldSnookerID":0,"LiveUrl":"","DetailsUrl":"","PointsDropped":false,"ShowCommonNote":true,"Estimated":false,"Type":1,"TableNo":0,"VideoURL":"","InitDate":"2023-10-27T08:07:51Z","ModDate":"2023-12-02T18:59:54Z","StartDate":"2023-12-02T18:59:54Z","EndDate":"2023-12-02T22:45:11Z","ScheduledDate":"2023-12-02T19:00:00Z","FrameScores":"93-40 (60), 0-84 (50), 15-71, 63-24, 0-124 (124)<br/>99-1, 110-17 (110), 7-117 (105), 126-2 (88)<br/>85-38 (84)","Sessions":"","Note":"","ExtendedNote":"","HeldOver":false,"StatsURL":""},{"ID":8483189,"EventID":1451,"Round":14,"Number":2,"Player1ID":5,"Score1":6,"Walkover1":false,"Player2ID":666,"Score2":2,"Walkover2":false,"WinnerID":5,"Unfinished":false,"OnBreak":false,"Status":3,"WorldSnookerID":0,"LiveUrl":"","DetailsUrl":"","PointsDropped":false,"ShowCommonNote":true,"Estimated":false,"Type":1,"TableNo":0,"VideoURL":"","InitDate":"2023-10-27T08:07:51Z","ModDate":"2024-01-31T21:02:49Z","StartDate":"2023-12-02T12:52:42Z","EndDate":"2023-12-02T15:35:39Z","ScheduledDate":"2023-12-02T13:00:00Z","FrameScores":"86-37 (54), 113-0 (113), 0-112 (112), 14-66<br/>95-0 (60), 82-21 (52), 82-38 (50), 102-19 (90)","Sessions":"","Note":"","ExtendedNote":"","HeldOver":false,"StatsURL":""},{"ID":8325458,"EventID":1451,"Round":13,"Number":1,"Player1ID":224,"Score1":6,"Walkover1":false,"Player2ID":1,"Score2":5,"Walkover2":false,"WinnerID":224,"Unfinished":false,"OnBreak":false,"Status":3,"WorldSnookerID":0,"LiveUrl":"","DetailsUrl":"","PointsDropped":false,"ShowCommonNote":true,"Estimated":false,"Type":1,"TableNo":0,"VideoURL":"","InitDate":"2023-10-27T08:07:39Z","ModDate":"2023-12-01T19:11:21Z","StartDate":"2023-12-01T19:11:21Z","EndDate":"2023-12-01T23:44:59Z","ScheduledDate":"2023-12-01T19:00:00Z","FrameScores":"","Sessions":"","Note":"A new record of 195 points scored in frame 8 as Williams won it by 101-94. The previous record was 192.","ExtendedNote":"","HeldOver":false,"StatsURL":""},{"ID":8325459,"EventID":1451,"Round":13,"Number":2,"Player1ID":17,"Score1":3,"Walkover1":false,"Player2ID":12,"Score2":6,"Walkover2":false,"WinnerID":12,"Unfinished":false,"OnBreak":false,"Status":3,"WorldSnookerID":0,"LiveUrl":"","DetailsUrl":"","PointsDropped":false,"ShowCommonNote":true,"Estimated":false,"Type":1,"TableNo":0,"VideoURL":"","InitDate":"2023-10-27T08:07:39Z","ModDate":"2023-12-01T19:11:21Z","StartDate":"2023-12-01T19:11:21Z","EndDate":"2023-12-01T22:12:32Z","ScheduledDate":"2023-12-01T19:00:00Z","FrameScores":"","Sessions":"","Note":"This was Trump's 1000th win in professional snooker. ","ExtendedNote":"Re-rack in frame 3. ","HeldOver":false,"StatsURL":""},{"ID":8325460,"EventID":1451,"Round":13,"Number":3,"Player1ID":5,"Score1":6,"Walkover1":false,"Player2ID":906,"Score2":5,"Walkover2":false,"WinnerID":5,"Unfinished":false,"OnBreak":false,"Status":3,"WorldSnookerID":0,"LiveUrl":"","DetailsUrl":"","PointsDropped":false,"ShowCommonNote":true,"Estimated":false,"Type":1,"TableNo":0,"VideoURL":"","InitDate":"2023-10-27T08:07:39Z","ModDate":"2023-12-01T13:00:57Z","StartDate":"2023-12-01T13:00:57Z","EndDate":"2023-12-01T16:43:24Z","ScheduledDate":"2023-12-01T13:00:00Z","FrameScores":"","Sessions":"","Note":"O'Sullivan's becomes the first player to win 100 matches at the UK Championship","ExtendedNote":"","HeldOver":false,"StatsURL":""},{"ID":8325461,"EventID":1451,"Round":13,"Number":4,"Player1ID":666,"Score1":6,"Walkover1":false,"Player2ID":81,"Score2":4,"Walkover2":false,"WinnerID":666,"Unfinished":false,"OnBreak":false,"Status":3,"WorldSnookerID":0,"LiveUrl":"","DetailsUrl":"","PointsDropped":false,"ShowCommonNote":true,"Estimated":false,"Type":1,"TableNo":0,"VideoURL":"","InitDate":"2023-10-27T08:07:39Z","ModDate":"2023-12-01T13:00:57Z","StartDate":"2023-12-01T13:00:57Z","EndDate":"2023-12-01T16:48:54Z","ScheduledDate":"2023-12-01T13:00:00Z","FrameScores":"","Sessions":"","Note":"","ExtendedNote":"","HeldOver":false,"StatsURL":""},{"ID":8324485,"EventID":1451,"Round":8,"Number":1,"Player1ID":224,"Score1":6,"Walkover1":false,"Player2ID":8,"Score2":3,"Walkover2":false,"WinnerID":224,"Unfinished":false,"OnBreak":false,"Status":3,"WorldSnookerID":0,"LiveUrl":"","DetailsUrl":"","PointsDropped":false,"ShowCommonNote":true,"Estimated":false,"Type":1,"TableNo":0,"VideoURL":"","InitDate":"2023-11-08T20:33:24Z","ModDate":"2023-11-29T12:50:36Z","StartDate":"2023-11-29T12:50:36Z","EndDate":"2023-11-29T16:14:25Z","ScheduledDate":"2023-11-29T13:00:00Z","FrameScores":"","Sessions":"","Note":"","ExtendedNote":"","HeldOver":false,"StatsURL":""},{"ID":8324486,"EventID":1451,"Round":8,"Number":2,"Player1ID":1,"Score1":6,"Walkover1":false,"Player2ID":106,"Score2":4,"Walkover2":false,"WinnerID":1,"Unfinished":false,"OnBreak":false,"Status":3,"WorldSnookerID":0,"LiveUrl":"","DetailsUrl":"","PointsDropped":false,"ShowCommonNote":true,"Estimated":false,"Type":1,"TableNo":0,"VideoURL":"","InitDate":"2023-11-08T20:33:24Z","ModDate":"2023-11-29T19:05:59Z","StartDate":"2023-11-29T19:05:59Z","EndDate":"2023-11-29T23:04:28Z","ScheduledDate":"2023-11-29T19:00:00Z","FrameScores":"","Sessions":"","Note":"","ExtendedNote":"","HeldOver":false,"StatsURL":""},{"ID":8324487,"EventID":1451,"Round":8,"Number":3,"Player1ID":17,"Score1":6,"Walkover1":false,"Player2ID":16,"Score2":5,"Walkover2":false,"WinnerID":17,"Unfinished":false,"OnBreak":false,"Status":3,"WorldSnookerID":0,"LiveUrl":"","DetailsUrl":"","PointsDropped":false,"ShowCommonNote":true,"Estimated":false,"Type":1,"TableNo":0,"VideoURL":"","InitDate":"2023-11-08T20:33:24Z","ModDate":"2023-11-29T19:05:59Z","StartDate":"2023-11-29T19:05:59Z","EndDate":"2023-11-29T23:20:48Z","ScheduledDate":"2023-11-29T19:00:00Z","FrameScores":"","Sessions":"","Note":"","ExtendedNote":"","HeldOver":false,"StatsURL":""},{"ID":8324488,"EventID":1451,"Round":8,"Number":4,"Player1ID":10,"Score1":0,"Walkover1":false,"Player2ID":12,"Score2":6,"Walkover2":false,"WinnerID":12,"Unfinished":false,"OnBreak":false,"Status":3,"WorldSnookerID":0,"LiveUrl":"","DetailsUrl":"","PointsDropped":false,"ShowCommonNote":true,"Estimated":false,"Type":1,"TableNo":0,"VideoURL":"","InitDate":"2023-11-08T20:33:24Z","ModDate":"2023-11-29T12:50:36Z","StartDate":"2023-11-29T12:50:36Z","EndDate":"2023-11-29T15:33:37Z","ScheduledDate":"2023-11-29T13:00:00Z","FrameScores":"","Sessions":"","Note":"","ExtendedNote":"","HeldOver":false,"StatsURL":""},{"ID":8324489,"EventID":1451,"Round":8,"Number":5,"Player1ID":5,"Score1":6,"Walkover1":false,"Player2ID":92,"Score2":5,"Walkover2":false,"WinnerID":5,"Unfinished":false,"OnBreak":false,"Status":3,"WorldSnookerID":0,"LiveUrl":"","DetailsUrl":"","PointsDropped":false,"ShowCommonNote":true,"Estimated":false,"Type":1,"TableNo":0,"VideoURL":"","InitDate":"2023-11-08T20:33:24Z","ModDate":"2023-11-30T13:08:53Z","StartDate":"2023-11-30T13:08:53Z","EndDate":"2023-11-30T16:14:46Z","ScheduledDate":"2023-11-30T13:00:00Z","FrameScores":"","Sessions":"","Note":"","ExtendedNote":"","HeldOver":false,"StatsURL":""},{"ID":8324490,"EventID":1451,"Round":8,"Number":6,"Player1ID":237,"Score1":3,"Walkover1":false,"Player2ID":906,"Score2":6,"Walkover2":false,"WinnerID":906,"Unfinished":false,"OnBreak":false,"Status":3,"WorldSnookerID":0,"LiveUrl":"","DetailsUrl":"","PointsDropped":false,"ShowCommonNote":true,"Estimated":false,"Type":1,"TableNo":0,"VideoURL":"","InitDate":"2023-11-08T20:33:24Z","ModDate":"2023-11-30T13:08:53Z","StartDate":"2023-11-30T13:08:53Z","EndDate":"2023-11-30T16:33:55Z","ScheduledDate":"2023-11-30T13:00:00Z","FrameScores":"","Sessions":"","Note":"","ExtendedNote":"","HeldOver":false,"StatsURL":""},{"ID":8324491,"EventID":1451,"Round":8,"Number":7,"Player1ID":666,"Score1":6,"Walkover1":false,"Player2ID":47,"Score2":1,"Walkover2":false,"WinnerID":666,"Unfinished":false,"OnBreak":false,"Status":3,"WorldSnookerID":0,"LiveUrl":"","DetailsUrl":"","PointsDropped":false,"ShowCommonNote":true,"Estimated":false,"Type":1,"TableNo":0,"VideoURL":"","InitDate":"2023-11-08T20:33:24Z","ModDate":"2023-11-30T19:29:35Z","StartDate":"2023-11-30T19:29:35Z","EndDate":"2023-11-30T21:14:31Z","ScheduledDate":"2023-11-30T19:00:00Z","FrameScores":"","Sessions":"","Note":"","ExtendedNote":"","HeldOver":false,"StatsURL":""},{"ID":8324492,"EventID":1451,"Round":8,"Number":8,"Player1ID":81,"Score1":6,"Walkover1":false,"Player2ID":101,"Score2":4,"Walkover2":false,"WinnerID":81,"Unfinished":false,"OnBreak":false,"Status":3,"WorldSnookerID":0,"LiveUrl":"","DetailsUrl":"","PointsDropped":false,"ShowCommonNote":true,"Estimated":false,"Type":1,"TableNo":0,"VideoURL":"","InitDate":"2023-11-08T20:33:24Z","ModDate":"2023-11-30T19:29:35Z","StartDate":"2023-11-30T19:29:35Z","EndDate":"2023-11-30T22:24:49Z","ScheduledDate":"2023-11-30T19:00:00Z","FrameScores":"","Sessions":"","Note":"","ExtendedNote":"","HeldOver":false,"StatsURL":""},{"ID":8322469,"EventID":1451,"Round":7,"Number":1,"Player1ID":202,"Score1":5,"Walkover1":false,"Player2ID":224,"Score2":6,"Walkover2":false,"WinnerID":224,"Unfinished":false,"OnBreak":false,"Status":3,"WorldSnookerID":0,"LiveUrl":"","DetailsUrl":"","PointsDropped":false,"ShowCommonNote":true,"Estimated":false,"Type":1,"TableNo":0,"VideoURL":"","InitDate":"2023-11-08T20:32:36Z","ModDate":"2023-11-25T13:01:47Z","StartDate":"2023-11-25T13:01:47Z","EndDate":"2023-11-25T17:42:32Z","ScheduledDate":"2023-11-25T13:00:00Z","FrameScores":"","Sessions":"","Note":"","ExtendedNote":"","HeldOver":false,"StatsURL":""},{"ID":8322470,"EventID":1451,"Round":7,"Number":2,"Player1ID":8,"Score1":6,"Walkover1":false,"Player2ID":208,"Score2":5,"Walkover2":false,"WinnerID":8,"Unfinished":false,"OnBreak":false,"Status":3,"WorldSnookerID":0,"LiveUrl":"","DetailsUrl":"","PointsDropped":false,"ShowCommonNote":true,"Estimated":false,"Type":1,"TableNo":0,"VideoURL":"","InitDate":"2023-11-08T20:32:36Z","ModDate":"2023-11-25T19:04:44Z","StartDate":"2023-11-25T19:04:44Z","EndDate":"2023-11-25T22:46:48Z","ScheduledDate":"2023-11-25T19:00:00Z","FrameScores":"","Sessions":"","Note":"Ford was 5-1 down","ExtendedNote":"","HeldOver":false,"StatsURL":""},{"ID":8322471,"EventID":1451,"Round":7,"Number":3,"Player1ID":1,"Score1":6,"Walkover1":false,"Player2ID":1417,"Score2":4,"Walkover2":false,"WinnerID":1,"Unfinished":false,"OnBreak":false,"Status":3,"WorldSnookerID":0,"LiveUrl":"","DetailsUrl":"","PointsDropped":false,"ShowCommonNote":true,"Estimated":false,"Type":1,"TableNo":0,"VideoURL":"","InitDate":"2023-11-08T20:32:36Z","ModDate":"2023-11-25T13:01:47Z","StartDate":"2023-11-25T13:01:47Z","EndDate":"2023-11-25T17:19:14Z","ScheduledDate":"2023-11-25T13:00:00Z","FrameScores":"","Sessions":"","Note":"","ExtendedNote":"","HeldOver":false,"StatsURL":""},{"ID":8322472,"EventID":1451,"Round":7,"Number":4,"Player1ID":39,"Score1":5,"Walkover1":false,"Player2ID":106,"Score2":6,"Walkover2":false,"WinnerID":106,"Unfinished":false,"OnBreak":false,"Status":3,"WorldSnookerID":0,"LiveUrl":"","DetailsUrl":"","PointsDropped":false,"ShowCommonNote":true,"Estimated":false,"Type":1,"TableNo":0,"VideoURL":"","InitDate":"2023-11-08T20:32:36Z","ModDate":"2023-11-25T19:04:44Z","StartDate":"2023-11-25T19:04:44Z","EndDate":"2023-11-25T23:09:09Z","ScheduledDate":"2023-11-25T19:00:00Z","FrameScores":"","Sessions":"","Note":"Clarke was 5-1 down","ExtendedNote":"","HeldOver":false,"StatsURL":""},{"ID":8322473,"EventID":1451,"Round":7,"Number":5,"Player1ID":17,"Score1":6,"Walkover1":false,"Player2ID":48,"Score2":0,"Walkover2":false,"WinnerID":17,"Unfinished":false,"OnBreak":false,"Status":3,"WorldSnookerID":0,"LiveUrl":"","DetailsUrl":"","PointsDropped":false,"ShowCommonNote":true,"Estimated":false,"Type":1,"TableNo":0,"VideoURL":"","InitDate":"2023-11-08T20:32:36Z","ModDate":"2023-11-27T19:04:31Z","StartDate":"2023-11-27T19:04:31Z","EndDate":"2023-11-27T21:16:34Z","ScheduledDate":"2023-11-27T19:00:00Z","FrameScores":"","Sessions":"","Note":"","ExtendedNote":"","HeldOver":false,"StatsURL":""},{"ID":8322474,"EventID":1451,"Round":7,"Number":6,"Player1ID":16,"Score1":6,"Walkover1":false,"Player2ID":19,"Score2":4,"Walkover2":false,"WinnerID":16,"Unfinished":false,"OnBreak":false,"Status":3,"WorldSnookerID":0,"LiveUrl":"","DetailsUrl":"","PointsDropped":false,"ShowCommonNote":true,"Estimated":false,"Type":1,"TableNo":0,"VideoURL":"","InitDate":"2023-11-08T20:32:36Z","ModDate":"2023-11-27T13:04:09Z","StartDate":"2023-11-27T13:04:09Z","EndDate":"2023-11-27T17:14:00Z","ScheduledDate":"2023-11-27T13:00:00Z","FrameScores":"","Sessions":"","Note":"","ExtendedNote":"","HeldOver":false,"StatsURL":""},{"ID":8322475,"EventID":1451,"Round":7,"Number":7,"Player1ID":85,"Score1":4,"Walkover1":false,"Player2ID":10,"Score2":6,"Walkover2":false,"WinnerID":10,"Unfinished":false,"OnBreak":false,"Status":3,"WorldSnookerID":0,"LiveUrl":"","DetailsUrl":"","PointsDropped":false,"ShowCommonNote":true,"Estimated":false,"Type":1,"TableNo":0,"VideoURL":"","InitDate":"2023-11-08T20:32:36Z","ModDate":"2023-11-27T19:04:31Z","StartDate":"2023-11-27T19:04:31Z","EndDate":"2023-11-27T22:57:43Z","ScheduledDate":"2023-11-27T19:00:00Z","FrameScores":"","Sessions":"","Note":"Re-spotted black in frame 2.","ExtendedNote":"","HeldOver":false,"StatsURL":""},{"ID":8322476,"EventID":1451,"Round":7,"Number":8,"Player1ID":12,"Score1":6,"Walkover1":false,"Player2ID":1257,"Score2":1,"Walkover2":false,"WinnerID":12,"Unfinished":false,"OnBreak":false,"Status":3,"WorldSnookerID":0,"LiveUrl":"","DetailsUrl":"","PointsDropped":false,"ShowCommonNote":true,"Estimated":false,"Type":1,"TableNo":0,"VideoURL":"","InitDate":"2023-11-08T20:32:36Z","ModDate":"2023-11-27T13:04:09Z","StartDate":"2023-11-27T13:04:09Z","EndDate":"2023-11-27T16:36:03Z","ScheduledDate":"2023-11-27T13:00:00Z","FrameScores":"","Sessions":"","Note":"","ExtendedNote":"","HeldOver":false,"StatsURL":""},{"ID":8322477,"EventID":1451,"Round":7,"Number":9,"Player1ID":5,"Score1":6,"Walkover1":false,"Player2ID":22,"Score2":2,"Walkover2":false,"WinnerID":5,"Unfinished":false,"OnBreak":false,"Status":3,"WorldSnookerID":0,"LiveUrl":"","DetailsUrl":"","PointsDropped":false,"ShowCommonNote":true,"Estimated":false,"Type":1,"TableNo":0,"VideoURL":"","InitDate":"2023-11-08T20:32:36Z","ModDate":"2023-11-28T13:14:24Z","StartDate":"2023-11-28T13:14:24Z","EndDate":"2023-11-28T16:17:17Z","ScheduledDate":"2023-11-28T13:00:00Z","FrameScores":"","Sessions":"","Note":"","ExtendedNote":"","HeldOver":false,"StatsURL":""},{"ID":8322478,"EventID":1451,"Round":7,"Number":10,"Player1ID":92,"Score1":6,"Walkover1":false,"Player2ID":217,"Score2":5,"Walkover2":false,"WinnerID":92,"Unfinished":false,"OnBreak":false,"Status":3,"WorldSnookerID":0,"LiveUrl":"","DetailsUrl":"","PointsDropped":false,"ShowCommonNote":true,"Estimated":false,"Type":1,"TableNo":0,"VideoURL":"","InitDate":"2023-11-08T20:32:36Z","ModDate":"2023-11-28T18:48:34Z","StartDate":"2023-11-28T18:48:34Z","EndDate":"2023-11-28T22:23:34Z","ScheduledDate":"2023-11-28T19:00:00Z","FrameScores":"","Sessions":"","Note":"Milkins was on a 147 in frame 5 but missed the last red.","ExtendedNote":"","HeldOver":false,"StatsURL":""},{"ID":8322479,"EventID":1451,"Round":7,"Number":11,"Player1ID":237,"Score1":6,"Walkover1":false,"Player2ID":1038,"Score2":3,"Walkover2":false,"WinnerID":237,"Unfinished":false,"OnBreak":false,"Status":3,"WorldSnookerID":0,"LiveUrl":"","DetailsUrl":"","PointsDropped":false,"ShowCommonNote":true,"Estimated":false,"Type":1,"TableNo":0,"VideoURL":"","InitDate":"2023-11-08T20:32:36Z","ModDate":"2023-11-28T13:14:24Z","StartDate":"2023-11-28T13:14:24Z","EndDate":"2023-11-28T16:18:18Z","ScheduledDate":"2023-11-28T13:00:00Z","FrameScores":"","Sessions":"","Note":"","ExtendedNote":"","HeldOver":false,"StatsURL":""},{"ID":8322480,"EventID":1451,"Round":7,"Number":12,"Player1ID":154,"Score1":2,"Walkover1":false,"Player2ID":906,"Score2":6,"Walkover2":false,"WinnerID":906,"Unfinished":false,"OnBreak":false,"Status":3,"WorldSnookerID":0,"LiveUrl":"","DetailsUrl":"","PointsDropped":false,"ShowCommonNote":true,"Estimated":false,"Type":1,"TableNo":0,"VideoURL":"","InitDate":"2023-11-08T20:32:36Z","ModDate":"2023-11-28T18:48:34Z","StartDate":"2023-11-28T18:48:34Z","EndDate":"2023-11-28T21:48:13Z","ScheduledDate":"2023-11-28T19:00:00Z","FrameScores":"","Sessions":"","Note":"","ExtendedNote":"","HeldOver":false,"StatsURL":""},{"ID":8322481,"EventID":1451,"Round":7,"Number":13,"Player1ID":97,"Score1":4,"Walkover1":false,"Player2ID":666,"Score2":6,"Walkover2":false,"WinnerID":666,"Unfinished":false,"OnBreak":false,"Status":3,"WorldSnookerID":0,"LiveUrl":"","DetailsUrl":"","PointsDropped":false,"ShowCommonNote":true,"Estimated":true,"Type":1,"TableNo":0,"VideoURL":"","InitDate":"2023-11-08T20:32:36Z","ModDate":"2023-11-26T20:01:48Z","StartDate":"2023-11-26T20:01:48Z","EndDate":"2023-11-27T00:02:44Z","ScheduledDate":"2023-11-26T20:00:00Z","FrameScores":"","Sessions":"","Note":"re-rack in frame 3","ExtendedNote":"The match was delayed due to a fire alarm in the arena.","HeldOver":false,"StatsURL":""},{"ID":8322482,"EventID":1451,"Round":7,"Number":14,"Player1ID":158,"Score1":3,"Walkover1":false,"Player2ID":47,"Score2":6,"Walkover2":false,"WinnerID":47,"Unfinished":false,"OnBreak":false,"Status":3,"WorldSnookerID":0,"LiveUrl":"","DetailsUrl":"","PointsDropped":false,"ShowCommonNote":true,"Estimated":true,"Type":1,"TableNo":0,"VideoURL":"","InitDate":"2023-11-08T20:32:36Z","ModDate":"2023-11-26T20:01:48Z","StartDate":"2023-11-26T20:01:48Z","EndDate":"2023-11-26T23:24:01Z","ScheduledDate":"2023-11-26T20:00:00Z","FrameScores":"","Sessions":"","Note":"","ExtendedNote":"The match was delayed due to a fire alarm in the arena.","HeldOver":false,"StatsURL":""},{"ID":8322483,"EventID":1451,"Round":7,"Number":15,"Player1ID":81,"Score1":6,"Walkover1":false,"Player2ID":608,"Score2":5,"Walkover2":false,"WinnerID":81,"Unfinished":false,"OnBreak":false,"Status":3,"WorldSnookerID":0,"LiveUrl":"","DetailsUrl":"","PointsDropped":false,"ShowCommonNote":true,"Estimated":false,"Type":1,"TableNo":0,"VideoURL":"","InitDate":"2023-11-08T20:32:36Z","ModDate":"2023-11-26T13:12:47Z","StartDate":"2023-11-26T13:12:47Z","EndDate":"2023-11-26T18:36:32Z","ScheduledDate":"2023-11-26T13:00:00Z","FrameScores":"","Sessions":"","Note":"Zhang's maximum attempt in frame 2 ended at 96.","ExtendedNote":"","HeldOver":false,"StatsURL":""},{"ID":8322484,"EventID":1451,"Round":7,"Number":16,"Player1ID":101,"Score1":6,"Walkover1":false,"Player2ID":1108,"Score2":4,"Walkover2":false,"WinnerID":101,"Unfinished":false,"OnBreak":false,"Status":3,"WorldSnookerID":0,"LiveUrl":"","DetailsUrl":"","PointsDropped":false,"ShowCommonNote":true,"Estimated":false,"Type":1,"TableNo":0,"VideoURL":"","InitDate":"2023-11-08T20:32:36Z","ModDate":"2023-11-26T13:12:47Z","StartDate":"2023-11-26T13:12:47Z","EndDate":"2023-11-26T16:58:46Z","ScheduledDate":"2023-11-26T13:00:00Z","FrameScores":"","Sessions":"","Note":"","ExtendedNote":"","HeldOver":false,"StatsURL":""}]