[{"ID":7965407,"EventID":1461,"Round":15,"Number":1,"Player1ID":97,"Score1":3,"Walkover1":false,"Player2ID":1,"Score2":0,"Walkover2":false,"WinnerID":97,"Unfinished":false,"OnBreak":false,"Status":3,"WorldSnookerID":0,"LiveUrl":"","DetailsUrl":"https://scores.wst.tv/matches/cd2af3f8-c846-4fc7-a2ea-fe34bfbdbd71","PointsDropped":false,"ShowCommonNote":true,"Estimated":true,"Type":1,"TableNo":0,"VideoURL":"","InitDate":"2023-06-10T08:49:09Z","ModDate":"2023-07-21T20:53:15Z","StartDate":"2023-07-21T20:53:15Z","EndDate":"2023-07-21T21:46:39Z","ScheduledDate":"2023-07-21T20:30:00Z","FrameScores":"65-53, 73-0 (73), 69-30 (69)","Sessions":"","Note":"Referee: Dave Ford<br/><br/>This was Murphy's 12th ranking title.","ExtendedNote":"","HeldOver":false,"StatsURL":""}]